arcade_datadog_api/__init__.py
arcade_datadog_api/moar/Datadog.json
arcade_datadog_api/moar/openapi.json
arcade_datadog_api/tools/__init__.py
arcade_datadog_api/tools/request_body_schemas.py
arcade_datadog_api/wrapper_tools/AcknowledgeOnCallPage.json
arcade_datadog_api/wrapper_tools/ActivateAwsScanOptions.json
arcade_datadog_api/wrapper_tools/ActivateAzureScanOptions.json
arcade_datadog_api/wrapper_tools/ActivateGcpScanOptions.json
arcade_datadog_api/wrapper_tools/AddCommentToCase.json
arcade_datadog_api/wrapper_tools/AddDashboardsToList.json
arcade_datadog_api/wrapper_tools/AddMemberTeamToSuperTeam.json
arcade_datadog_api/wrapper_tools/AddPermissionToRole.json
arcade_datadog_api/wrapper_tools/AddReadRoleToArchive.json
arcade_datadog_api/wrapper_tools/AddRoleToRestrictionQuery.json
arcade_datadog_api/wrapper_tools/AddTeamLink.json
arcade_datadog_api/wrapper_tools/AddUserToRole.json
arcade_datadog_api/wrapper_tools/AddUserToTeam.json
arcade_datadog_api/wrapper_tools/AggregateLogs.json
arcade_datadog_api/wrapper_tools/AggregatePipelineEvents.json
arcade_datadog_api/wrapper_tools/AggregateRumEvents.json
arcade_datadog_api/wrapper_tools/AggregateSpansMetrics.json
arcade_datadog_api/wrapper_tools/AggregateTestMetrics.json
arcade_datadog_api/wrapper_tools/ArchiveAzureCostAccount.json
arcade_datadog_api/wrapper_tools/ArchiveCase.json
arcade_datadog_api/wrapper_tools/ArchiveCloudCostAccount.json
arcade_datadog_api/wrapper_tools/ArchiveGcpCostManagementAccount.json
arcade_datadog_api/wrapper_tools/AssignCaseToUser.json
arcade_datadog_api/wrapper_tools/BulkDeleteDatastoreItems.json
arcade_datadog_api/wrapper_tools/BulkUpdateDatastoreItems.json
arcade_datadog_api/wrapper_tools/CancelDowntime.json
arcade_datadog_api/wrapper_tools/CancelHistoricalJob.json
arcade_datadog_api/wrapper_tools/CancelWorkflowInstance.json
arcade_datadog_api/wrapper_tools/ChangeSignalState.json
arcade_datadog_api/wrapper_tools/CloneExistingRole.json
arcade_datadog_api-2.0.0.dist-info/METADATA
arcade_datadog_api-2.0.0.dist-info/WHEEL
arcade_datadog_api-2.0.0.dist-info/entry_points.txt
arcade_datadog_api-2.0.0.dist-info/licenses/LICENSE
arcade_datadog_api-2.0.0.dist-info/RECORD
